README.md
setup.py
alibabacloud_gateway_fc_util/__init__.py
alibabacloud_gateway_fc_util/client.py
alibabacloud_gateway_fc_util.egg-info/PKG-INFO
alibabacloud_gateway_fc_util.egg-info/SOURCES.txt
alibabacloud_gateway_fc_util.egg-info/dependency_links.txt
alibabacloud_gateway_fc_util.egg-info/requires.txt
alibabacloud_gateway_fc_util.egg-info/top_level.txt